rate_limiter/__init__.py
rate_limiter/config.py
rate_limiter/flask_decorator.py
rate_limiter/main.py
rate_limiter/metrics.py
rate_limiter/rate_lmiter.py
flask_rate_limiter_lite-0.1.5.dist-info/METADATA
flask_rate_limiter_lite-0.1.5.dist-info/WHEEL
flask_rate_limiter_lite-0.1.5.dist-info/top_level.txt
flask_rate_limiter_lite-0.1.5.dist-info/RECORD
