Metadata-Version: 2.4
Name: flask-rate-limiter-lite
Version: 0.1.5
Author: Aayushi Singh
Requires-Python: >=3.9
Requires-Dist: flask
Requires-Dist: pydantic
Dynamic: author
Dynamic: description
Dynamic: description-content-type
Dynamic: requires-dist
Dynamic: requires-python
